wowcher/__init__.py
wowcher/api.py
wowcher/frame.py
wowcher/mock/__init__.py
wowcher/mock/api_mock.py
wowcher/mock/frame_mock.py
wowcher_api_python-1.0.5.dist-info/METADATA
wowcher_api_python-1.0.5.dist-info/WHEEL
wowcher_api_python-1.0.5.dist-info/licenses/LICENSE
wowcher_api_python-1.0.5.dist-info/RECORD
