Metadata-Version: 2.3
Name: wowcher-api-python
Version: 1.0.5
Summary: Library for integration with Wowcher.App api application
Project-URL: Homepage, https://github.com/dev-self-team/wowcher-api-python
Project-URL: Issues, https://github.com/dev-self-team/wowcher-api-python/issues
Author-email: Self <dev@self.team>
License-File: LICENSE
Classifier: License :: OSI Approved :: MIT License
Classifier: Operating System :: OS Independent
Classifier: Programming Language :: Python :: 3
Requires-Python: >=3.8
